obj_encrypt/__init__.py
obj_encrypt-0.7.0.dist-info/LICENSE
obj_encrypt-0.7.0.dist-info/METADATA
obj_encrypt-0.7.0.dist-info/WHEEL
obj_encrypt-0.7.0.dist-info/top_level.txt
obj_encrypt-0.7.0.dist-info/RECORD
