Metadata-Version: 2.1
Name: obj-encrypt
Version: 0.7.0
Summary: obj-encrypt is an encryption library based on the AES-256 algorithm. It uses Python objects as the basic unit, which can convert objects into binary ciphertext and support decryption. Objects encrypted with obj-encrypt support TCP communication, database storage, and more.
Home-page: UNKNOWN
Author: Cyberbolt
Author-email: dtconlyone@gmail.com
License: UNKNOWN
Platform: UNKNOWN
Classifier: Programming Language :: Python :: 3
Classifier: License :: OSI Approved :: MIT License
Classifier: Operating System :: OS Independent
License-File: LICENSE
Requires-Dist: pycryptodome (>=3.14.1)
